mlop/__init__.py
mlop/__main__.py
mlop/compat/__init__.py
mlop/compat/lightning.py
mlop/compat/neptune.py
mlop/compat/torch.py
mlop/compat/transformers.py
pluto/__init__.py
pluto/__main__.py
pluto/api.py
pluto/auth.py
pluto/compat/__init__.py
pluto/compat/lightning.py
pluto/compat/neptune.py
pluto/compat/torch.py
pluto/compat/transformers.py
pluto/data.py
pluto/file.py
pluto/iface.py
pluto/init.py
pluto/log.py
pluto/op.py
pluto/sets.py
pluto/store.py
pluto/sync/__init__.py
pluto/sync/__main__.py
pluto/sync/process.py
pluto/sync/store.py
pluto/sys.py
pluto/util.py
pluto_ml_nightly-0.0.4.dev20260201105510.dist-info/LICENSE
pluto_ml_nightly-0.0.4.dev20260201105510.dist-info/METADATA
pluto_ml_nightly-0.0.4.dev20260201105510.dist-info/WHEEL
pluto_ml_nightly-0.0.4.dev20260201105510.dist-info/entry_points.txt
pluto_ml_nightly-0.0.4.dev20260201105510.dist-info/RECORD
